mockbinn/__init__.py
mockbinn/core.py
mockbinn/utils.py
mockbinn/generators/__init__.py
mockbinn/generators/address.py
mockbinn/generators/base.py
mockbinn/generators/boolean.py
mockbinn/generators/date.py
mockbinn/generators/email.py
mockbinn/generators/item.py
mockbinn/generators/name.py
mockbinn/generators/number.py
mockbinn/generators/phone.py
mockbinn/generators/uuid.py
mockbinn-0.1.2.dist-info/licenses/LICENSE
mockbinn-0.1.2.dist-info/METADATA
mockbinn-0.1.2.dist-info/WHEEL
mockbinn-0.1.2.dist-info/top_level.txt
mockbinn-0.1.2.dist-info/RECORD
