Metadata-Version: 2.4
Name: mockbinn
Version: 0.1.2
Summary: Uma biblioteca para gerar dados fictícios para testes
Home-page: https://github.com/NathanBin/mockbinn
Author: Nathan
Author-email: nathan.lopes@sptech.school
Classifier: Programming Language :: Python :: 3
Classifier: License :: OSI Approved :: MIT License
Classifier: Operating System :: OS Independent
Requires-Python: >=3.6
License-File: LICENSE
Provides-Extra: parquet
Requires-Dist: pyarrow>=6.0.0; extra == "parquet"
Provides-Extra: dev
Requires-Dist: pytest>=6.0.0; extra == "dev"
Requires-Dist: twine>=3.0.0; extra == "dev"
Provides-Extra: all
Requires-Dist: pyarrow>=6.0.0; extra == "all"
Dynamic: author
Dynamic: author-email
Dynamic: classifier
Dynamic: description
Dynamic: description-content-type
Dynamic: home-page
Dynamic: license-file
Dynamic: provides-extra
Dynamic: requires-python
Dynamic: summary
